dqframework/__init__.py
dqframework/pipeline/__init__.py
dqframework/validators/__init__.py
dqframework/validators/base_validator.py
dqframework/validators/check_operators.py
dqframework/validators/comparisons_operator.py
dqframework/validators/has_between.py
dqframework/validators/has_date_pattern.py
dqframework/validators/has_max.py
dqframework/validators/has_mean.py
dqframework/validators/has_min.py
dqframework/validators/has_str_length.py
dqframework/validators/has_str_length_between.py
dqframework/validators/has_str_max_length.py
dqframework/validators/has_str_min_length.py
dqframework/validators/has_str_pattern.py
dqframework/validators/is_complete.py
dqframework/validators/is_composite_key.py
dqframework/validators/is_in.py
dqframework/validators/is_unique.py
dqframework/validators/no_future_dates.py
dqframework-0.6.1.dist-info/licenses/LICENSE
dqframework-0.6.1.dist-info/METADATA
dqframework-0.6.1.dist-info/WHEEL
dqframework-0.6.1.dist-info/top_level.txt
dqframework-0.6.1.dist-info/RECORD
