Metadata-Version: 2.4
Name: dqframework
Version: 0.6.1
Summary: A dq framework
Author-email: Hugo Martins <hugo.martins365@gmail.com>
Requires-Python: >=3.8
License-File: LICENSE
Dynamic: license-file
